[
  {
    "date": "2026-06-14",
    "pt_html_path": "edicoes/2026-06-14/index.html",
    "es_html_path": "edicoes/2026-06-14/es/index.html",
    "pt_pdf_path": "arquivos/clippings/2026-06-14/panorama-mobilidade-latam-2026-06-14-pt.pdf",
    "es_pdf_path": "arquivos/clippings/2026-06-14/panorama-mobilidade-latam-2026-06-14-es.pdf",
    "pt_title": "PANORAMA MOBILIDADE LATAM — 14/06/2026 — teste editorial revisado",
    "pt_html_url": "https://panoramamobilidade.github.io/edicoes/2026-06-14/index.html",
    "pt_pdf_url": "https://panoramamobilidade.github.io/arquivos/clippings/2026-06-14/panorama-mobilidade-latam-2026-06-14-pt.pdf",
    "pt_pdf_size": 181239,
    "es_title": "PANORAMA MOBILIDADE LATAM — 14/06/2026 — prueba editorial revisada",
    "es_html_url": "https://panoramamobilidade.github.io/edicoes/2026-06-14/es/index.html",
    "es_pdf_url": "https://panoramamobilidade.github.io/arquivos/clippings/2026-06-14/panorama-mobilidade-latam-2026-06-14-es.pdf",
    "es_pdf_size": 181006
  },
  {
    "date": "2026-06-15",
    "pt_html_path": "edicoes/2026-06-15/index.html",
    "es_html_path": "edicoes/2026-06-15/es/index.html",
    "pt_pdf_path": "arquivos/clippings/2026-06-15/panorama-mobilidade-latam-2026-06-15-pt.pdf",
    "es_pdf_path": "arquivos/clippings/2026-06-15/panorama-mobilidade-latam-2026-06-15-es.pdf",
    "pt_title": "PANORAMA MOBILIDADE LATAM — 15 de junho de 2026",
    "pt_html_url": "https://panoramamobilidade.github.io/edicoes/2026-06-15/index.html",
    "pt_pdf_url": "https://panoramamobilidade.github.io/arquivos/clippings/2026-06-15/panorama-mobilidade-latam-2026-06-15-pt.pdf",
    "pt_pdf_size": 166352,
    "es_title": "PANORAMA MOVILIDAD LATAM — 15 de junio de 2026",
    "es_html_url": "https://panoramamobilidade.github.io/edicoes/2026-06-15/es/index.html",
    "es_pdf_url": "https://panoramamobilidade.github.io/arquivos/clippings/2026-06-15/panorama-mobilidade-latam-2026-06-15-es.pdf",
    "es_pdf_size": 165570
  },
  {
    "date": "2026-06-18",
    "pt_html_path": "edicoes/2026-06-18/index.html",
    "es_html_path": "edicoes/2026-06-18/es/index.html",
    "pt_pdf_path": "arquivos/clippings/2026-06-18/panorama-mobilidade-latam-2026-06-18-pt.pdf",
    "es_pdf_path": "arquivos/clippings/2026-06-18/panorama-mobilidade-latam-2026-06-18-es.pdf",
    "pt_title": "PANORAMA MOBILIDADE LATAM — 18 de junho de 2026",
    "pt_html_url": "https://panoramamobilidade.github.io/edicoes/2026-06-18/index.html",
    "pt_pdf_url": "https://panoramamobilidade.github.io/arquivos/clippings/2026-06-18/panorama-mobilidade-latam-2026-06-18-pt.pdf",
    "pt_pdf_size": 166960,
    "es_title": "PANORAMA MOVILIDAD LATAM — 18 de junio de 2026",
    "es_html_url": "https://panoramamobilidade.github.io/edicoes/2026-06-18/es/index.html",
    "es_pdf_url": "https://panoramamobilidade.github.io/arquivos/clippings/2026-06-18/panorama-mobilidade-latam-2026-06-18-es.pdf",
    "es_pdf_size": 166793
  },
  {
    "date": "2026-06-19",
    "pt_html_path": "edicoes/2026-06-19/index.html",
    "es_html_path": "edicoes/2026-06-19/es/index.html",
    "pt_pdf_path": "arquivos/clippings/2026-06-19/panorama-mobilidade-latam-2026-06-19-pt.pdf",
    "es_pdf_path": "arquivos/clippings/2026-06-19/panorama-mobilidade-latam-2026-06-19-es.pdf",
    "pt_title": "PANORAMA MOBILIDADE LATAM — 19 de junho de 2026",
    "pt_html_url": "https://panoramamobilidade.github.io/edicoes/2026-06-19/index.html",
    "pt_pdf_url": "https://panoramamobilidade.github.io/arquivos/clippings/2026-06-19/panorama-mobilidade-latam-2026-06-19-pt.pdf",
    "pt_pdf_size": 176180,
    "es_title": "PANORAMA MOVILIDAD LATAM — 19 de junio de 2026",
    "es_html_url": "https://panoramamobilidade.github.io/edicoes/2026-06-19/es/index.html",
    "es_pdf_url": "https://panoramamobilidade.github.io/arquivos/clippings/2026-06-19/panorama-mobilidade-latam-2026-06-19-es.pdf",
    "es_pdf_size": 175541
  },
  {
    "date": "2026-06-22",
    "pt_html_path": "edicoes/2026-06-22/index.html",
    "es_html_path": "edicoes/2026-06-22/es/index.html",
    "pt_pdf_path": "arquivos/clippings/2026-06-22/panorama-mobilidade-latam-2026-06-22-pt.pdf",
    "es_pdf_path": "arquivos/clippings/2026-06-22/panorama-mobilidade-latam-2026-06-22-es.pdf",
    "pt_title": "PANORAMA MOBILIDADE LATAM — 22 de junho de 2026",
    "pt_html_url": "https://panoramamobilidade.github.io/edicoes/2026-06-22/index.html",
    "pt_pdf_url": "https://panoramamobilidade.github.io/arquivos/clippings/2026-06-22/panorama-mobilidade-latam-2026-06-22-pt.pdf",
    "pt_pdf_size": 195930,
    "es_title": "PANORAMA MOVILIDAD LATAM — 22 de junho de 2026",
    "es_html_url": "https://panoramamobilidade.github.io/edicoes/2026-06-22/es/index.html",
    "es_pdf_url": "https://panoramamobilidade.github.io/arquivos/clippings/2026-06-22/panorama-mobilidade-latam-2026-06-22-es.pdf",
    "es_pdf_size": 195090
  },
  {
    "date": "2026-06-23",
    "pt_html_path": "edicoes/2026-06-23/index.html",
    "es_html_path": "edicoes/2026-06-23/es/index.html",
    "pt_pdf_path": "arquivos/clippings/2026-06-23/panorama-mobilidade-latam-2026-06-23-pt.pdf",
    "es_pdf_path": "arquivos/clippings/2026-06-23/panorama-mobilidade-latam-2026-06-23-es.pdf",
    "pt_title": "PANORAMA MOBILIDADE LATAM — 23 de junho de 2026",
    "pt_html_url": "https://panoramamobilidade.github.io/edicoes/2026-06-23/index.html",
    "pt_pdf_url": "https://panoramamobilidade.github.io/arquivos/clippings/2026-06-23/panorama-mobilidade-latam-2026-06-23-pt.pdf",
    "pt_pdf_size": 185049,
    "es_title": "PANORAMA MOVILIDAD LATAM — 23 de junho de 2026",
    "es_html_url": "https://panoramamobilidade.github.io/edicoes/2026-06-23/es/index.html",
    "es_pdf_url": "https://panoramamobilidade.github.io/arquivos/clippings/2026-06-23/panorama-mobilidade-latam-2026-06-23-es.pdf",
    "es_pdf_size": 184649
  },
  {
    "date": "2026-06-24",
    "pt_html_path": "edicoes/2026-06-24/index.html",
    "es_html_path": "edicoes/2026-06-24/es/index.html",
    "pt_pdf_path": "arquivos/clippings/2026-06-24/panorama-mobilidade-latam-2026-06-24-pt.pdf",
    "es_pdf_path": "arquivos/clippings/2026-06-24/panorama-mobilidade-latam-2026-06-24-es.pdf",
    "pt_title": "PANORAMA MOBILIDADE LATAM — 24 de junho de 2026",
    "pt_html_url": "https://panoramamobilidade.github.io/edicoes/2026-06-24/index.html",
    "pt_pdf_url": "https://panoramamobilidade.github.io/arquivos/clippings/2026-06-24/panorama-mobilidade-latam-2026-06-24-pt.pdf",
    "pt_pdf_size": 191374,
    "es_title": "PANORAMA MOVILIDAD LATAM — 24 de junho de 2026",
    "es_html_url": "https://panoramamobilidade.github.io/edicoes/2026-06-24/es/index.html",
    "es_pdf_url": "https://panoramamobilidade.github.io/arquivos/clippings/2026-06-24/panorama-mobilidade-latam-2026-06-24-es.pdf",
    "es_pdf_size": 190962
  },
  {
    "date": "2026-06-25",
    "pt_html_path": "edicoes/2026-06-25/index.html",
    "es_html_path": "edicoes/2026-06-25/es/index.html",
    "pt_pdf_path": "arquivos/clippings/2026-06-25/panorama-mobilidade-latam-2026-06-25-pt.pdf",
    "es_pdf_path": "arquivos/clippings/2026-06-25/panorama-mobilidade-latam-2026-06-25-es.pdf",
    "pt_title": "PANORAMA MOBILIDADE LATAM — 25 de junho de 2026",
    "pt_html_url": "https://panoramamobilidade.github.io/edicoes/2026-06-25/index.html",
    "pt_pdf_url": "https://panoramamobilidade.github.io/arquivos/clippings/2026-06-25/panorama-mobilidade-latam-2026-06-25-pt.pdf",
    "pt_pdf_size": 192217,
    "es_title": "PANORAMA MOVILIDAD LATAM — 25 de junho de 2026",
    "es_html_url": "https://panoramamobilidade.github.io/edicoes/2026-06-25/es/index.html",
    "es_pdf_url": "https://panoramamobilidade.github.io/arquivos/clippings/2026-06-25/panorama-mobilidade-latam-2026-06-25-es.pdf",
    "es_pdf_size": 191594
  },
  {
    "date": "2026-06-26",
    "pt_html_path": "edicoes/2026-06-26/index.html",
    "es_html_path": "edicoes/2026-06-26/es/index.html",
    "pt_pdf_path": "arquivos/clippings/2026-06-26/panorama-mobilidade-latam-2026-06-26-pt.pdf",
    "es_pdf_path": "arquivos/clippings/2026-06-26/panorama-mobilidade-latam-2026-06-26-es.pdf",
    "pt_title": "PANORAMA MOBILIDADE LATAM — 26 de junho de 2026",
    "pt_html_url": "https://panoramamobilidade.github.io/edicoes/2026-06-26/index.html",
    "pt_pdf_url": "https://panoramamobilidade.github.io/arquivos/clippings/2026-06-26/panorama-mobilidade-latam-2026-06-26-pt.pdf",
    "pt_pdf_size": 430019,
    "es_title": "PANORAMA MOVILIDAD LATAM — 26 de junho de 2026",
    "es_html_url": "https://panoramamobilidade.github.io/edicoes/2026-06-26/es/index.html",
    "es_pdf_url": "https://panoramamobilidade.github.io/arquivos/clippings/2026-06-26/panorama-mobilidade-latam-2026-06-26-es.pdf",
    "es_pdf_size": 429545
  },
  {
    "date": "2026-06-29",
    "pt_html_path": "edicoes/2026-06-29/index.html",
    "es_html_path": "edicoes/2026-06-29/es/index.html",
    "pt_pdf_path": "arquivos/clippings/2026-06-29/panorama-mobilidade-latam-2026-06-29-pt.pdf",
    "es_pdf_path": "arquivos/clippings/2026-06-29/panorama-mobilidade-latam-2026-06-29-es.pdf",
    "pt_title": "PANORAMA MOBILIDADE LATAM — 29 de junho de 2026",
    "pt_html_url": "https://panoramamobilidade.github.io/edicoes/2026-06-29/index.html",
    "pt_pdf_url": "https://panoramamobilidade.github.io/arquivos/clippings/2026-06-29/panorama-mobilidade-latam-2026-06-29-pt.pdf",
    "pt_pdf_size": 285630,
    "es_title": "PANORAMA MOVILIDAD LATAM — 29 de junho de 2026",
    "es_html_url": "https://panoramamobilidade.github.io/edicoes/2026-06-29/es/index.html",
    "es_pdf_url": "https://panoramamobilidade.github.io/arquivos/clippings/2026-06-29/panorama-mobilidade-latam-2026-06-29-es.pdf",
    "es_pdf_size": 285532
  },
  {
    "date": "2026-06-30",
    "pt_html_path": "edicoes/2026-06-30/index.html",
    "es_html_path": "edicoes/2026-06-30/es/index.html",
    "pt_pdf_path": "arquivos/clippings/2026-06-30/panorama-mobilidade-latam-2026-06-30-pt.pdf",
    "es_pdf_path": "arquivos/clippings/2026-06-30/panorama-mobilidade-latam-2026-06-30-es.pdf",
    "pt_title": "PANORAMA MOBILIDADE LATAM — 30 de junho de 2026",
    "pt_html_url": "https://panoramamobilidade.github.io/edicoes/2026-06-30/index.html",
    "pt_pdf_url": "https://panoramamobilidade.github.io/arquivos/clippings/2026-06-30/panorama-mobilidade-latam-2026-06-30-pt.pdf",
    "pt_pdf_size": 189814,
    "es_title": "PANORAMA MOVILIDAD LATAM — 30 de junho de 2026",
    "es_html_url": "https://panoramamobilidade.github.io/edicoes/2026-06-30/es/index.html",
    "es_pdf_url": "https://panoramamobilidade.github.io/arquivos/clippings/2026-06-30/panorama-mobilidade-latam-2026-06-30-es.pdf",
    "es_pdf_size": 189440
  },
  {
    "date": "2026-07-01",
    "pt_html_path": "edicoes/2026-07-01/index.html",
    "es_html_path": "edicoes/2026-07-01/es/index.html",
    "pt_pdf_path": "arquivos/clippings/2026-07-01/panorama-mobilidade-latam-2026-07-01-pt.pdf",
    "es_pdf_path": "arquivos/clippings/2026-07-01/panorama-mobilidade-latam-2026-07-01-es.pdf",
    "pt_title": "PANORAMA MOBILIDADE LATAM — 1º de julho de 2026",
    "pt_html_url": "https://panoramamobilidade.github.io/edicoes/2026-07-01/index.html",
    "pt_pdf_url": "https://panoramamobilidade.github.io/arquivos/clippings/2026-07-01/panorama-mobilidade-latam-2026-07-01-pt.pdf",
    "pt_pdf_size": 88829,
    "es_title": "PANORAMA MOVILIDAD LATAM — 1 de julio de 2026",
    "es_html_url": "https://panoramamobilidade.github.io/edicoes/2026-07-01/es/index.html",
    "es_pdf_url": "https://panoramamobilidade.github.io/arquivos/clippings/2026-07-01/panorama-mobilidade-latam-2026-07-01-es.pdf",
    "es_pdf_size": 89636
  },
  {
    "date": "2026-07-02",
    "pt_html_path": "edicoes/2026-07-02/index.html",
    "es_html_path": "edicoes/2026-07-02/es/index.html",
    "pt_pdf_path": "arquivos/clippings/2026-07-02/panorama-mobilidade-latam-2026-07-02-pt.pdf",
    "es_pdf_path": "arquivos/clippings/2026-07-02/panorama-mobilidade-latam-2026-07-02-es.pdf",
    "pt_title": "PANORAMA MOBILIDADE LATAM — 2 de julho de 2026",
    "pt_html_url": "https://panoramamobilidade.github.io/edicoes/2026-07-02/index.html",
    "pt_pdf_url": "https://panoramamobilidade.github.io/arquivos/clippings/2026-07-02/panorama-mobilidade-latam-2026-07-02-pt.pdf",
    "pt_pdf_size": 168214,
    "es_title": "PANORAMA MOVILIDAD LATAM — 2 de julio de 2026",
    "es_html_url": "https://panoramamobilidade.github.io/edicoes/2026-07-02/es/index.html",
    "es_pdf_url": "https://panoramamobilidade.github.io/arquivos/clippings/2026-07-02/panorama-mobilidade-latam-2026-07-02-es.pdf",
    "es_pdf_size": 168036
  },
  {
    "date": "2026-07-03",
    "pt_html_path": "edicoes/2026-07-03/index.html",
    "es_html_path": "edicoes/2026-07-03/es/index.html",
    "pt_pdf_path": "arquivos/clippings/2026-07-03/panorama-mobilidade-latam-2026-07-03-pt.pdf",
    "es_pdf_path": "arquivos/clippings/2026-07-03/panorama-mobilidade-latam-2026-07-03-es.pdf",
    "pt_title": "PANORAMA MOBILIDADE LATAM — 3 de julho de 2026",
    "pt_html_url": "https://panoramamobilidade.github.io/edicoes/2026-07-03/index.html",
    "pt_pdf_url": "https://panoramamobilidade.github.io/arquivos/clippings/2026-07-03/panorama-mobilidade-latam-2026-07-03-pt.pdf",
    "pt_pdf_size": 170311,
    "es_title": "PANORAMA MOVILIDAD LATAM — 3 de julio de 2026",
    "es_html_url": "https://panoramamobilidade.github.io/edicoes/2026-07-03/es/index.html",
    "es_pdf_url": "https://panoramamobilidade.github.io/arquivos/clippings/2026-07-03/panorama-mobilidade-latam-2026-07-03-es.pdf",
    "es_pdf_size": 170426
  },
  {
    "date": "2026-07-04",
    "pt_html_path": "edicoes/2026-07-04/index.html",
    "es_html_path": "edicoes/2026-07-04/es/index.html",
    "pt_pdf_path": "arquivos/clippings/2026-07-04/panorama-mobilidade-latam-2026-07-04-pt.pdf",
    "es_pdf_path": "arquivos/clippings/2026-07-04/panorama-mobilidade-latam-2026-07-04-es.pdf",
    "pt_title": "PANORAMA MOBILIDADE LATAM — 4 de julho de 2026",
    "pt_html_url": "https://panoramamobilidade.github.io/edicoes/2026-07-04/index.html",
    "pt_pdf_url": "https://panoramamobilidade.github.io/arquivos/clippings/2026-07-04/panorama-mobilidade-latam-2026-07-04-pt.pdf",
    "pt_pdf_size": 161253,
    "es_title": "PANORAMA MOVILIDAD LATAM — 4 de julio de 2026",
    "es_html_url": "https://panoramamobilidade.github.io/edicoes/2026-07-04/es/index.html",
    "es_pdf_url": "https://panoramamobilidade.github.io/arquivos/clippings/2026-07-04/panorama-mobilidade-latam-2026-07-04-es.pdf",
    "es_pdf_size": 161762
  },
  {
    "date": "2026-07-06",
    "pt_html_path": "edicoes/2026-07-06/index.html",
    "es_html_path": "edicoes/2026-07-06/es/index.html",
    "pt_pdf_path": "arquivos/clippings/2026-07-06/panorama-mobilidade-latam-2026-07-06-pt.pdf",
    "es_pdf_path": "arquivos/clippings/2026-07-06/panorama-mobilidade-latam-2026-07-06-es.pdf",
    "pt_title": "PANORAMA MOBILIDADE LATAM — 6 de julho de 2026",
    "pt_html_url": "https://panoramamobilidade.github.io/edicoes/2026-07-06/index.html",
    "pt_pdf_url": "https://panoramamobilidade.github.io/arquivos/clippings/2026-07-06/panorama-mobilidade-latam-2026-07-06-pt.pdf",
    "pt_pdf_size": 122348,
    "es_title": "PANORAMA MOVILIDAD LATAM — 6 de julio de 2026",
    "es_html_url": "https://panoramamobilidade.github.io/edicoes/2026-07-06/es/index.html",
    "es_pdf_url": "https://panoramamobilidade.github.io/arquivos/clippings/2026-07-06/panorama-mobilidade-latam-2026-07-06-es.pdf",
    "es_pdf_size": 122504
  },
  {
    "date": "2026-07-07",
    "pt_html_path": "edicoes/2026-07-07/index.html",
    "es_html_path": "edicoes/2026-07-07/es/index.html",
    "pt_pdf_path": "arquivos/clippings/2026-07-07/panorama-mobilidade-latam-2026-07-07-pt.pdf",
    "es_pdf_path": "arquivos/clippings/2026-07-07/panorama-mobilidade-latam-2026-07-07-es.pdf",
    "pt_title": "PANORAMA MOBILIDADE LATAM — 7 de julho de 2026",
    "pt_html_url": "https://panoramamobilidade.github.io/edicoes/2026-07-07/index.html",
    "pt_pdf_url": "https://panoramamobilidade.github.io/arquivos/clippings/2026-07-07/panorama-mobilidade-latam-2026-07-07-pt.pdf",
    "pt_pdf_size": 204737,
    "es_title": "PANORAMA MOVILIDAD LATAM — 7 de julio de 2026",
    "es_html_url": "https://panoramamobilidade.github.io/edicoes/2026-07-07/es/index.html",
    "es_pdf_url": "https://panoramamobilidade.github.io/arquivos/clippings/2026-07-07/panorama-mobilidade-latam-2026-07-07-es.pdf",
    "es_pdf_size": 204593
  },
  {
    "date": "2026-07-08",
    "pt_html_path": "edicoes/2026-07-08/index.html",
    "es_html_path": "edicoes/2026-07-08/es/index.html",
    "pt_pdf_path": "arquivos/clippings/2026-07-08/panorama-mobilidade-latam-2026-07-08-pt.pdf",
    "es_pdf_path": "arquivos/clippings/2026-07-08/panorama-mobilidade-latam-2026-07-08-es.pdf",
    "pt_title": "PANORAMA MOBILIDADE LATAM — 8 de julho de 2026",
    "pt_html_url": "https://panoramamobilidade.github.io/edicoes/2026-07-08/index.html",
    "pt_pdf_url": "https://panoramamobilidade.github.io/arquivos/clippings/2026-07-08/panorama-mobilidade-latam-2026-07-08-pt.pdf",
    "pt_pdf_size": 230571,
    "es_title": "PANORAMA MOVILIDAD LATAM — 8 de julho de 2026",
    "es_html_url": "https://panoramamobilidade.github.io/edicoes/2026-07-08/es/index.html",
    "es_pdf_url": "https://panoramamobilidade.github.io/arquivos/clippings/2026-07-08/panorama-mobilidade-latam-2026-07-08-es.pdf",
    "es_pdf_size": 230781
  },
  {
    "date": "2026-07-09",
    "pt_html_path": "edicoes/2026-07-09/index.html",
    "es_html_path": "edicoes/2026-07-09/es/index.html",
    "pt_pdf_path": "arquivos/clippings/2026-07-09/panorama-mobilidade-latam-2026-07-09-pt.pdf",
    "es_pdf_path": "arquivos/clippings/2026-07-09/panorama-mobilidade-latam-2026-07-09-es.pdf",
    "pt_title": "PANORAMA MOBILIDADE LATAM — 9 de julho de 2026",
    "pt_html_url": "https://panoramamobilidade.github.io/edicoes/2026-07-09/index.html",
    "pt_pdf_url": "https://panoramamobilidade.github.io/arquivos/clippings/2026-07-09/panorama-mobilidade-latam-2026-07-09-pt.pdf",
    "pt_pdf_size": 240335,
    "es_title": "PANORAMA MOVILIDAD LATAM — 9 de julio de 2026",
    "es_html_url": "https://panoramamobilidade.github.io/edicoes/2026-07-09/es/index.html",
    "es_pdf_url": "https://panoramamobilidade.github.io/arquivos/clippings/2026-07-09/panorama-mobilidade-latam-2026-07-09-es.pdf",
    "es_pdf_size": 240491
  },
  {
    "date": "2026-07-10",
    "pt_html_path": "edicoes/2026-07-10/index.html",
    "es_html_path": "edicoes/2026-07-10/es/index.html",
    "pt_pdf_path": "arquivos/clippings/2026-07-10/panorama-mobilidade-latam-2026-07-10-pt.pdf",
    "es_pdf_path": "arquivos/clippings/2026-07-10/panorama-mobilidade-latam-2026-07-10-es.pdf",
    "pt_title": "PANORAMA MOBILIDADE LATAM — 10 de julho de 2026",
    "pt_html_url": "https://panoramamobilidade.github.io/edicoes/2026-07-10/index.html",
    "pt_pdf_url": "https://panoramamobilidade.github.io/arquivos/clippings/2026-07-10/panorama-mobilidade-latam-2026-07-10-pt.pdf",
    "pt_pdf_size": 209322,
    "es_title": "PANORAMA MOVILIDAD LATAM — 10 de julio de 2026",
    "es_html_url": "https://panoramamobilidade.github.io/edicoes/2026-07-10/es/index.html",
    "es_pdf_url": "https://panoramamobilidade.github.io/arquivos/clippings/2026-07-10/panorama-mobilidade-latam-2026-07-10-es.pdf",
    "es_pdf_size": 209551
  }
]